{
  "project_info": {
    "project_number": "14148390258",
    "project_id": "mediapp-60ec0",
    "storage_bucket": "mediapp-60ec0.appspot.com"
  },
  "client": [
    {
      "client_info": {
        "mobilesdk_app_id": "1:14148390258:android:3cd8bcb2bd68bf5d7de1eb",
        "android_client_info": {
          "package_name": "com.example.mediapp"
        }
      },
      "oauth_client": [
        {
          "client_id": "14148390258-1e4pkdpci8jlpp6ilf0nuifgpkuvespa.apps.googleusercontent.com",
          "client_type": 3
        }
      ],
      "api_key": [
        {
          "current_key": "AIzaSyBb189B64D0mfbvirxtSNVNm7EUCcvvOg0"
        }
      ],
      "services": {
        "appinvite_service": {
          "other_platform_oauth_client": [
            {
              "client_id": "14148390258-1e4pkdpci8jlpp6ilf0nuifgpkuvespa.apps.googleusercontent.com",
              "client_type": 3
            }
          ]
        }
      }
    }
  ],
  "configuration_version": "1"
}